[
  {
    "comment": "", 
    "definition": "Oxygen + 2 Ascorbate <=> 2 Dehydroascorbate + 2 H2O", 
    "orthologs": {
      "K00423": "L-ascorbate oxidase [EC:1.10.3.3]"
    }, 
    "name": "L-ascorbate:oxygen oxidoreductase", 
    "product_stoichiometries": [
      "2", 
      "2"
    ], 
    "enzymes": [
      "1.10.3.3"
    ], 
    "equation": "C00007 + 2 C00072 <=> 2 C05422 + 2 C00001", 
    "glycans": false, 
    "substrate_stoichiometries": [
      "2", 
      "1"
    ], 
    "rpairs": {}, 
    "entry_id": "R00068", 
    "pathways": {
      "rn00053": "Ascorbate and aldarate metabolism", 
      "rn01100": "Metabolic pathways"
    }, 
    "products": [
      "C05422", 
      "C00001"
    ], 
    "substrates": [
      "C00072", 
      "C00007"
    ]
  }
]