[
  {
    "comment": "multi-step reaction", 
    "definition": "S-Adenosyl-L-homocysteine + H2O <=> Adenosine + L-Homocysteine", 
    "orthologs": {
      "K01251": "adenosylhomocysteinase [EC:3.3.1.1]"
    }, 
    "name": "S-Adenosyl-L-homocysteine hydrolase", 
    "product_stoichiometries": [
      "1", 
      "1"
    ], 
    "enzymes": [
      "3.3.1.1"
    ], 
    "equation": "C00021 + C00001 <=> C00212 + C00155", 
    "glycans": false, 
    "substrate_stoichiometries": [
      "1", 
      "1"
    ], 
    "rpairs": {}, 
    "entry_id": "R00192", 
    "pathways": {
      "rn00270": "Cysteine and methionine metabolism", 
      "rn01100": "Metabolic pathways"
    }, 
    "products": [
      "C00212", 
      "C00155"
    ], 
    "substrates": [
      "C00021", 
      "C00001"
    ]
  }
]