[
  {
    "comment": "", 
    "definition": "Acyl-CoA + Acetate <=> Fatty acid anion + Acetyl-CoA", 
    "orthologs": {}, 
    "name": "Acyl-CoA:acetate CoA-transferase", 
    "product_stoichiometries": [
      "1", 
      "1"
    ], 
    "enzymes": [
      "2.8.3.8"
    ], 
    "equation": "C00040 + C00033 <=> C02403 + C00024", 
    "glycans": false, 
    "substrate_stoichiometries": [
      "1", 
      "1"
    ], 
    "rpairs": {}, 
    "entry_id": "R00393", 
    "pathways": {}, 
    "products": [
      "C02403", 
      "C00024"
    ], 
    "substrates": [
      "C00040", 
      "C00033"
    ]
  }
]