[
  {
    "comment": "", 
    "definition": "(4R)-4-Hydroxy-2-oxoglutarate <=> Pyruvate + Glyoxylate", 
    "orthologs": {
      "K18123": "4-hydroxy-2-oxoglutarate aldolase [EC:4.1.3.16]"
    }, 
    "name": "4-hydroxy-2-oxoglutarate glyoxylate-lyase (pyruvate-forming)", 
    "product_stoichiometries": [
      "1", 
      "1"
    ], 
    "enzymes": [
      "4.1.3.16"
    ], 
    "equation": "C05946 <=> C00022 + C00048", 
    "glycans": false, 
    "substrate_stoichiometries": [
      "1"
    ], 
    "rpairs": {}, 
    "entry_id": "R00471", 
    "pathways": {
      "rn00330": "Arginine and proline metabolism", 
      "rn01100": "Metabolic pathways"
    }, 
    "products": [
      "C00022", 
      "C00048"
    ], 
    "substrates": [
      "C05946"
    ]
  }
]