[
  {
    "comment": "", 
    "definition": "CTP + Pyruvate <=> CDP + Phosphoenolpyruvate", 
    "orthologs": {}, 
    "name": "CTP:pyruvate 2-O-phosphotransferase", 
    "product_stoichiometries": [
      "1", 
      "1"
    ], 
    "enzymes": [
      "2.7.1.40"
    ], 
    "equation": "C00063 + C00022 <=> C00112 + C00074", 
    "glycans": false, 
    "substrate_stoichiometries": [
      "1", 
      "1"
    ], 
    "rpairs": {}, 
    "entry_id": "R00572", 
    "pathways": {}, 
    "products": [
      "C00112", 
      "C00074"
    ], 
    "substrates": [
      "C00063", 
      "C00022"
    ]
  }
]