[
  {
    "comment": "", 
    "definition": "L-Serine <=> D-Serine", 
    "orthologs": {
      "K12235": "serine racemase [EC:5.1.1.18]"
    }, 
    "name": "serine racemase; L-2-Amino-3-hydroxypropionic acid racemase", 
    "product_stoichiometries": [
      "1"
    ], 
    "enzymes": [
      "5.1.1.10", 
      "5.1.1.18"
    ], 
    "equation": "C00065 <=> C00740", 
    "glycans": false, 
    "substrate_stoichiometries": [
      "1"
    ], 
    "rpairs": {}, 
    "entry_id": "R00589", 
    "pathways": {
      "rn01100": "Metabolic pathways", 
      "rn00260": "Glycine, serine and threonine metabolism"
    }, 
    "products": [
      "C00740"
    ], 
    "substrates": [
      "C00065"
    ]
  }
]