[
  {
    "comment": "multi-step reaction (ligating L-phenylalanine and [enzyme]-thiol, epimerizing and thioester-hydrolysing)", 
    "definition": "ATP + L-Phenylalanine + H2O <=> AMP + Diphosphate + D-Phenylalanine", 
    "orthologs": {}, 
    "name": "L-Phenylalanine racemase (ATP-hydrolysing)", 
    "product_stoichiometries": [
      "1", 
      "1", 
      "1"
    ], 
    "enzymes": [
      "5.1.1.11"
    ], 
    "equation": "C00002 + C00079 + C00001 <=> C00020 + C00013 + C02265", 
    "glycans": false, 
    "substrate_stoichiometries": [
      "1", 
      "1", 
      "1"
    ], 
    "rpairs": {}, 
    "entry_id": "R00686", 
    "pathways": {
      "rn00360": "Phenylalanine metabolism"
    }, 
    "products": [
      "C00020", 
      "C00013", 
      "C02265"
    ], 
    "substrates": [
      "C00002", 
      "C00079", 
      "C00001"
    ]
  }
]