[
  {
    "comment": "", 
    "definition": "2,3-Dihydroxybenzoate + Oxygen <=> 3-Carboxy-2-hydroxymuconate semialdehyde", 
    "orthologs": {
      "K10621": "2,3-dihydroxy-p-cumate/2,3-dihydroxybenzoate 3,4-dioxygenase [EC:1.13.11.- 1.13.11.14]"
    }, 
    "name": "2,3-dihydroxybenzoate:oxygen 3,4-oxidoreductase (decyclizing)", 
    "product_stoichiometries": [
      "1"
    ], 
    "enzymes": [
      "1.13.11.14"
    ], 
    "equation": "C00196 + C00007 <=> C04480", 
    "glycans": false, 
    "substrate_stoichiometries": [
      "1", 
      "1"
    ], 
    "rpairs": {}, 
    "entry_id": "R01507", 
    "pathways": {
      "rn00362": "Benzoate degradation", 
      "rn01120": "Microbial metabolism in diverse environments"
    }, 
    "products": [
      "C04480"
    ], 
    "substrates": [
      "C00196", 
      "C00007"
    ]
  }
]