[
  {
    "comment": "", 
    "definition": "(+)-Bornyl diphosphate <=> Geranyl diphosphate", 
    "orthologs": {
      "K15098": "bornyl diphosphate synthase [EC:5.5.1.8]"
    }, 
    "name": "(+)-Bornyl-diphosphate lyase (decyclizing)", 
    "product_stoichiometries": [
      "1"
    ], 
    "enzymes": [
      "5.5.1.8"
    ], 
    "equation": "C03190 <=> C00341", 
    "glycans": false, 
    "substrate_stoichiometries": [
      "1"
    ], 
    "rpairs": {}, 
    "entry_id": "R02007", 
    "pathways": {
      "rn01110": "Biosynthesis of secondary metabolites", 
      "rn00902": "Monoterpenoid biosynthesis", 
      "rn01100": "Metabolic pathways"
    }, 
    "products": [
      "C00341"
    ], 
    "substrates": [
      "C03190"
    ]
  }
]