[
  {
    "comment": "", 
    "definition": "UDP-glucose + Zeatin <=> UDP + O-beta-D-Glucosylzeatin", 
    "orthologs": {
      "K13492": "zeatin O-glucosyltransferase [EC:2.4.1.203]"
    }, 
    "name": "UDPglucose:zeatin O-beta-D-glucosyltransferase", 
    "product_stoichiometries": [
      "1", 
      "1"
    ], 
    "enzymes": [
      "2.4.1.203"
    ], 
    "equation": "C00029 + C00371 <=> C00015 + C03423", 
    "glycans": false, 
    "substrate_stoichiometries": [
      "1", 
      "1"
    ], 
    "rpairs": {}, 
    "entry_id": "R02118", 
    "pathways": {
      "rn01110": "Biosynthesis of secondary metabolites", 
      "rn00908": "Zeatin biosynthesis"
    }, 
    "products": [
      "C00015", 
      "C03423"
    ], 
    "substrates": [
      "C00029", 
      "C00371"
    ]
  }
]