[
  {
    "comment": "", 
    "definition": "Polyphosphate + D-Glucose <=> Polyphosphate + D-Glucose 6-phosphate", 
    "orthologs": {}, 
    "name": "Polyphosphate:D-glucose 6-phosphotransferase", 
    "product_stoichiometries": [
      "1", 
      "1"
    ], 
    "enzymes": [
      "2.7.1.63"
    ], 
    "equation": "C00404 + C00031 <=> C00404 + C00092", 
    "glycans": false, 
    "substrate_stoichiometries": [
      "1", 
      "1"
    ], 
    "rpairs": {}, 
    "entry_id": "R02185", 
    "pathways": {}, 
    "products": [
      "C00404", 
      "C00092"
    ], 
    "substrates": [
      "C00404", 
      "C00031"
    ]
  }
]