[
  {
    "comment": "", 
    "definition": "(R)-3-Hydroxybutanoyl-CoA <=> Crotonoyl-CoA + H2O", 
    "orthologs": {
      "K17865": "3-hydroxybutyryl-CoA dehydratase [EC:4.2.1.55]"
    }, 
    "name": "(3R)-3-hydroxybutanoyl-CoA hydro-lyase", 
    "product_stoichiometries": [
      "1", 
      "1"
    ], 
    "enzymes": [
      "4.2.1.55"
    ], 
    "equation": "C03561 <=> C00877 + C00001", 
    "glycans": false, 
    "substrate_stoichiometries": [
      "1"
    ], 
    "rpairs": {}, 
    "entry_id": "R03027", 
    "pathways": {
      "rn00650": "Butanoate metabolism", 
      "rn01120": "Microbial metabolism in diverse environments", 
      "rn00630": "Glyoxylate and dicarboxylate metabolism", 
      "rn01200": "Carbon metabolism"
    }, 
    "products": [
      "C00877", 
      "C00001"
    ], 
    "substrates": [
      "C03561"
    ]
  }
]