[
  {
    "comment": "", 
    "definition": "Ornithine + 2-Oxoglutarate <=> 5-Amino-2-oxopentanoic acid + L-Glutamate", 
    "orthologs": {}, 
    "name": "2,5-Diaminopentanoate:2-oxoglutarate aminotransferase", 
    "product_stoichiometries": [
      "1", 
      "1"
    ], 
    "enzymes": [
      "2.6.1.8"
    ], 
    "equation": "C01602 + C00026 <=> C01110 + C00025", 
    "glycans": false, 
    "substrate_stoichiometries": [
      "1", 
      "1"
    ], 
    "rpairs": {}, 
    "entry_id": "R03248", 
    "pathways": {}, 
    "products": [
      "C01110", 
      "C00025"
    ], 
    "substrates": [
      "C01602", 
      "C00026"
    ]
  }
]