[
  {
    "comment": "", 
    "definition": "Methylmalonate + CoA + ATP <=> (R)-Methylmalonyl-CoA + AMP + Diphosphate", 
    "orthologs": {
      "K18662": "malonyl-CoA/methylmalonyl-CoA synthetase [EC:6.2.1.-]", 
      "K18660": "malonyl-CoA/methylmalonyl-CoA synthetase [EC:6.2.1.-]", 
      "K18661": "malonyl-CoA/methylmalonyl-CoA synthetase [EC:6.2.1.-]"
    }, 
    "name": "methylmalonate:CoA ligase (AMP-forming)", 
    "product_stoichiometries": [
      "1", 
      "1", 
      "1"
    ], 
    "enzymes": [
      "6.2.1.-"
    ], 
    "equation": "C02170 + C00010 + C00002 <=> C01213 + C00020 + C00013", 
    "glycans": false, 
    "substrate_stoichiometries": [
      "1", 
      "1", 
      "1"
    ], 
    "rpairs": {}, 
    "entry_id": "R03383", 
    "pathways": {
      "rn00280": "Valine, leucine and isoleucine degradation"
    }, 
    "products": [
      "C01213", 
      "C00020", 
      "C00013"
    ], 
    "substrates": [
      "C02170", 
      "C00010", 
      "C00002"
    ]
  }
]