[
  {
    "comment": "", 
    "definition": "3alpha,7alpha,12beta-Trihydroxy-5beta-cholanate + NADP+ <=> 3alpha,7alpha-Dihydroxy-12-oxo-5beta-cholanate + NADPH + H+", 
    "orthologs": {}, 
    "name": "12beta-hydroxysteroid:NADP+ 12-oxidoreductase", 
    "product_stoichiometries": [
      "1", 
      "1", 
      "1"
    ], 
    "enzymes": [
      "1.1.1.238"
    ], 
    "equation": "C04661 + C00006 <=> C01292 + C00005 + C00080", 
    "glycans": false, 
    "substrate_stoichiometries": [
      "1", 
      "1"
    ], 
    "rpairs": {}, 
    "entry_id": "R03495", 
    "pathways": {}, 
    "products": [
      "C01292", 
      "C00005", 
      "C00080"
    ], 
    "substrates": [
      "C04661", 
      "C00006"
    ]
  }
]