[
  {
    "comment": "", 
    "definition": "(S)-Mandelate <=> (R)-Mandelate", 
    "orthologs": {
      "K01781": "mandelate racemase [EC:5.1.2.2]"
    }, 
    "name": "mandelate racemase", 
    "product_stoichiometries": [
      "1"
    ], 
    "enzymes": [
      "5.1.2.2"
    ], 
    "equation": "C01984 <=> C01983", 
    "glycans": false, 
    "substrate_stoichiometries": [
      "1"
    ], 
    "rpairs": {}, 
    "entry_id": "R03791", 
    "pathways": {
      "rn00627": "Aminobenzoate degradation", 
      "rn01120": "Microbial metabolism in diverse environments"
    }, 
    "products": [
      "C01983"
    ], 
    "substrates": [
      "C01984"
    ]
  }
]