[
  {
    "comment": "", 
    "definition": "ATP + 2-Succinylbenzoate + CoA <=> AMP + Diphosphate + 2-Succinylbenzoyl-CoA", 
    "orthologs": {
      "K01911": "O-succinylbenzoic acid---CoA ligase [EC:6.2.1.26]", 
      "K14760": "acyl-activating enzyme 14 [EC:6.2.1.26]"
    }, 
    "name": "O-Succinylbenzoate:CoA ligase (AMP-forming)", 
    "product_stoichiometries": [
      "1", 
      "1", 
      "1"
    ], 
    "enzymes": [
      "6.2.1.26"
    ], 
    "equation": "C00002 + C02730 + C00010 <=> C00020 + C00013 + C03160", 
    "glycans": false, 
    "substrate_stoichiometries": [
      "1", 
      "1", 
      "1"
    ], 
    "rpairs": {}, 
    "entry_id": "R04030", 
    "pathways": {
      "rn01110": "Biosynthesis of secondary metabolites", 
      "rn01100": "Metabolic pathways", 
      "rn00130": "Ubiquinone and other terpenoid-quinone biosynthesis"
    }, 
    "products": [
      "C00020", 
      "C00013", 
      "C03160"
    ], 
    "substrates": [
      "C00002", 
      "C02730", 
      "C00010"
    ]
  }
]