[
  {
    "comment": "", 
    "definition": "ATP + [Isocitrate dehydrogenase (NADP+)] <=> ADP + [Isocitrate dehydrogenase (NADP+)] phosphate", 
    "orthologs": {}, 
    "name": "ATP:[isocitrate dehydrogenase (NADP+)] phosphotransferase", 
    "product_stoichiometries": [
      "1", 
      "1"
    ], 
    "enzymes": [
      "2.7.11.5"
    ], 
    "equation": "C00002 + C04125 <=> C00008 + C04564", 
    "glycans": false, 
    "substrate_stoichiometries": [
      "1", 
      "1"
    ], 
    "rpairs": {}, 
    "entry_id": "R04401", 
    "pathways": {}, 
    "products": [
      "C00008", 
      "C04564"
    ], 
    "substrates": [
      "C00002", 
      "C04125"
    ]
  }
]