[
  {
    "comment": "", 
    "definition": "Parapyruvate + Ammonia <=> 4-Hydroxy-4-methylglutamate + H2O", 
    "orthologs": {}, 
    "name": "", 
    "product_stoichiometries": [
      "1", 
      "1"
    ], 
    "enzymes": [], 
    "equation": "C06033 + C00014 <=> C06034 + C00001", 
    "glycans": false, 
    "substrate_stoichiometries": [
      "1", 
      "1"
    ], 
    "rpairs": {}, 
    "entry_id": "R05077", 
    "pathways": {
      "rn00660": "C5-Branched dibasic acid metabolism"
    }, 
    "products": [
      "C06034", 
      "C00001"
    ], 
    "substrates": [
      "C06033", 
      "C00014"
    ]
  }
]