[
  {
    "comment": "", 
    "definition": "O-Phospho-4-hydroxy-L-threonine + H2O <=> 4-Hydroxy-L-threonine + Orthophosphate", 
    "orthologs": {
      "K01733": "threonine synthase [EC:4.2.3.1]"
    }, 
    "name": "O-Phospho-4-hydroxy-L-threonine phospho-lyase (adding water)", 
    "product_stoichiometries": [
      "1", 
      "1"
    ], 
    "enzymes": [
      "4.2.3.1"
    ], 
    "equation": "C06055 + C00001 <=> C06056 + C00009", 
    "glycans": false, 
    "substrate_stoichiometries": [
      "1", 
      "1"
    ], 
    "rpairs": {}, 
    "entry_id": "R05086", 
    "pathways": {
      "rn00750": "Vitamin B6 metabolism"
    }, 
    "products": [
      "C06056", 
      "C00009"
    ], 
    "substrates": [
      "C06055", 
      "C00001"
    ]
  }
]