[
  {
    "comment": "", 
    "definition": "Prostaglandin B2 <=> Prostaglandin C2", 
    "orthologs": {}, 
    "name": "", 
    "product_stoichiometries": [
      "1"
    ], 
    "enzymes": [], 
    "equation": "C05954 <=> C05955", 
    "glycans": false, 
    "substrate_stoichiometries": [
      "1"
    ], 
    "rpairs": {}, 
    "entry_id": "R05057", 
    "pathways": {
      "rn00590": "Arachidonic acid metabolism", 
      "rn01100": "Metabolic pathways"
    }, 
    "products": [
      "C05955"
    ], 
    "substrates": [
      "C05954"
    ]
  }
]