[
  {
    "comment": "see R05685 (NADH)", 
    "definition": "3-Methylbutanol + NADP+ <=> 3-Methylbutanal + NADPH + H+", 
    "orthologs": {}, 
    "name": "3-Methylbutanol:NADP oxidoreductase", 
    "product_stoichiometries": [
      "1", 
      "1", 
      "1"
    ], 
    "enzymes": [
      "1.1.1.265"
    ], 
    "equation": "C07328 + C00006 <=> C07329 + C00005 + C00080", 
    "glycans": false, 
    "substrate_stoichiometries": [
      "1", 
      "1"
    ], 
    "rpairs": {}, 
    "entry_id": "R05686", 
    "pathways": {}, 
    "products": [
      "C07329", 
      "C00005", 
      "C00080"
    ], 
    "substrates": [
      "C07328", 
      "C00006"
    ]
  }
]