[
  {
    "comment": "N,N-dimethyltransferase,TylM1", 
    "definition": "dTDP-3-amino-3,6-dideoxy-D-glucose + 2 S-Adenosyl-L-methionine <=> dTDP-D-mycaminose + 2 S-Adenosyl-L-homocysteine + 2 H+", 
    "orthologs": {
      "K13307": "dTDP-3-amino-3,6-dideoxy-alpha-D-glucopyranose N,N-dimethyltransferase [EC:2.1.1.235]"
    }, 
    "name": "S-adenosyl-L-methionine:dTDP-3-amino-3,6-dideoxy-alpha-D-glucopyranose 3-N,N-dimethyltransferase", 
    "product_stoichiometries": [
      "2", 
      "2", 
      "1"
    ], 
    "enzymes": [
      "2.1.1.235"
    ], 
    "equation": "C11925 + 2 C00019 <=> C11933 + 2 C00021 + 2 C00080", 
    "glycans": false, 
    "substrate_stoichiometries": [
      "2", 
      "1"
    ], 
    "rpairs": {}, 
    "entry_id": "R06439", 
    "pathways": {
      "rn01130": "Biosynthesis of antibiotics", 
      "rn00523": "Polyketide sugar unit biosynthesis"
    }, 
    "products": [
      "C00021", 
      "C00080", 
      "C11933"
    ], 
    "substrates": [
      "C00019", 
      "C11925"
    ]
  }
]