[
  {
    "comment": "8,8a-deoxyoleandolide synthase,OleA1-3", 
    "definition": "Malonyl-CoA + 6 Methylmalonyl-CoA + 6 NADPH + 6 H+ <=> 8,8a-Deoxyoleandolide + 7 CoA + 7 CO2 + H2O + 6 NADP+", 
    "orthologs": {
      "K16007": "8,8a-deoxyoleandolide synthase"
    }, 
    "name": "", 
    "product_stoichiometries": [
      "7", 
      "7", 
      "6", 
      "1", 
      "1"
    ], 
    "enzymes": [], 
    "equation": "C00083 + 6 C02557 + 6 C00005 + 6 C00080 <=> C11989 + 7 C00010 + 7 C00011 + C00001 + 6 C00006", 
    "glycans": false, 
    "substrate_stoichiometries": [
      "6", 
      "6", 
      "6", 
      "1"
    ], 
    "rpairs": {}, 
    "entry_id": "R06453", 
    "pathways": {
      "rn01130": "Biosynthesis of antibiotics", 
      "rn00522": "Biosynthesis of 12-, 14- and 16-membered macrolides"
    }, 
    "products": [
      "C00010", 
      "C00011", 
      "C00006", 
      "C11989", 
      "C00001"
    ], 
    "substrates": [
      "C02557", 
      "C00005", 
      "C00080", 
      "C00083"
    ]
  }
]