[
  {
    "comment": "", 
    "definition": "5-O-beta-D-Mycaminosyltylonolide + dTDP-6-deoxy-D-allose <=> Demethyllactenocin + dTDP", 
    "orthologs": {
      "K15993": "O-mycaminosyltylonolide 6-deoxyallosyltransferase [EC:2.4.1.317]"
    }, 
    "name": "dTDP-6-deoxy-alpha-D-allose:5-O-beta-D-mycaminosyltylonolide 23-O-6-deoxy-beta-D-allosyltransferase", 
    "product_stoichiometries": [
      "1", 
      "1"
    ], 
    "enzymes": [
      "2.4.1.317"
    ], 
    "equation": "C12002 + C11912 <=> C12003 + C00363", 
    "glycans": false, 
    "substrate_stoichiometries": [
      "1", 
      "1"
    ], 
    "rpairs": {}, 
    "entry_id": "R06451", 
    "pathways": {
      "rn01130": "Biosynthesis of antibiotics", 
      "rn00522": "Biosynthesis of 12-, 14- and 16-membered macrolides"
    }, 
    "products": [
      "C12003", 
      "C00363"
    ], 
    "substrates": [
      "C12002", 
      "C11912"
    ]
  }
]