[
  {
    "comment": "", 
    "definition": "3-(3-Hydroxyphenyl)propanoic acid + Oxygen + NADH + H+ <=> 3-(2,3-Dihydroxyphenyl)propanoate + H2O + NAD+", 
    "orthologs": {
      "K05712": "3-(3-hydroxy-phenyl)propionate hydroxylase [EC:1.14.13.127]"
    }, 
    "name": "3-(3-hydroxyphenyl)propanoate,NADH:oxygen oxidoreductase (2-hydroxylating)", 
    "product_stoichiometries": [
      "1", 
      "1", 
      "1"
    ], 
    "enzymes": [
      "1.14.13.127"
    ], 
    "equation": "C11457 + C00007 + C00004 + C00080 <=> C04044 + C00001 + C00003", 
    "glycans": false, 
    "substrate_stoichiometries": [
      "1", 
      "1", 
      "1", 
      "1"
    ], 
    "rpairs": {}, 
    "entry_id": "R06786", 
    "pathways": {
      "rn00360": "Phenylalanine metabolism", 
      "rn01120": "Microbial metabolism in diverse environments", 
      "rn01220": "Degradation of aromatic compounds"
    }, 
    "products": [
      "C04044", 
      "C00001", 
      "C00003"
    ], 
    "substrates": [
      "C11457", 
      "C00007", 
      "C00004", 
      "C00080"
    ]
  }
]