[
  {
    "comment": "", 
    "definition": "Hydrazine + 4 Ferricytochrome c <=> Nitrogen + 4 Ferrocytochrome c", 
    "orthologs": {
      "K20935": "hydrazine dehydrogenase [EC:1.7.2.8]"
    }, 
    "name": "hydrazine:ferricytochrome c oxidoreductase", 
    "product_stoichiometries": [
      "4", 
      "1"
    ], 
    "enzymes": [
      "1.7.2.8"
    ], 
    "equation": "C05361 + 4 C00125 <=> C00697 + 4 C00126", 
    "glycans": false, 
    "substrate_stoichiometries": [
      "4", 
      "1"
    ], 
    "rpairs": {}, 
    "entry_id": "R07174", 
    "pathways": {
      "rn00910": "Nitrogen metabolism", 
      "rn01120": "Microbial metabolism in diverse environments"
    }, 
    "products": [
      "C00126", 
      "C00697"
    ], 
    "substrates": [
      "C00125", 
      "C05361"
    ]
  }
]