[
  {
    "comment": "methoxyneurosporene dehydrogenase(crtD)", 
    "definition": "Chloroxanthin <=> Demethylspheroidene", 
    "orthologs": {
      "K09845": "1-hydroxycarotenoid 3,4-desaturase [EC:1.3.99.27]"
    }, 
    "name": "1-hydroxy-1,2-dihydrolycopene:acceptor oxidoreductase", 
    "product_stoichiometries": [
      "1"
    ], 
    "enzymes": [
      "1.3.99.27"
    ], 
    "equation": "C15892 <=> C15898", 
    "glycans": false, 
    "substrate_stoichiometries": [
      "1"
    ], 
    "rpairs": {}, 
    "entry_id": "R07534", 
    "pathways": {
      "rn00906": "Carotenoid biosynthesis", 
      "rn01100": "Metabolic pathways"
    }, 
    "products": [
      "C15898"
    ], 
    "substrates": [
      "C15892"
    ]
  }
]