[
  {
    "comment": "", 
    "definition": "S-(Indolylmethylthiohydroximoyl)-L-cysteine + H2O <=> Indolylmethylthiohydroximate + Pyruvate + Ammonia", 
    "orthologs": {
      "K11819": "S-alkyl-thiohydroximate lyase SUR1 [EC:4.4.1.-]"
    }, 
    "name": "", 
    "product_stoichiometries": [
      "1", 
      "1", 
      "1"
    ], 
    "enzymes": [
      "4.4.1.-"
    ], 
    "equation": "C16518 + C00001 <=> C16516 + C00022 + C00014", 
    "glycans": false, 
    "substrate_stoichiometries": [
      "1", 
      "1"
    ], 
    "rpairs": {}, 
    "entry_id": "R08170", 
    "pathways": {
      "rn01210": "2-Oxocarboxylic acid metabolism", 
      "rn01110": "Biosynthesis of secondary metabolites", 
      "rn00380": "Tryptophan metabolism", 
      "rn00966": "Glucosinolate biosynthesis"
    }, 
    "products": [
      "C16516", 
      "C00022", 
      "C00014"
    ], 
    "substrates": [
      "C16518", 
      "C00001"
    ]
  }
]