[
  {
    "comment": "unclear reaction (hydrolyzing, non-enzymatic or enzymatic)", 
    "definition": "5-Phenyl-1,3-oxazinane-2,4-dione + H2O <=> 3-Carbamoyl-2-phenylpropionic acid", 
    "orthologs": {}, 
    "name": "", 
    "product_stoichiometries": [
      "1"
    ], 
    "enzymes": [], 
    "equation": "C16596 + C00001 <=> C16591", 
    "glycans": false, 
    "substrate_stoichiometries": [
      "1", 
      "1"
    ], 
    "rpairs": {}, 
    "entry_id": "R08311", 
    "pathways": {
      "rn00982": "Drug metabolism - cytochrome P450"
    }, 
    "products": [
      "C16591"
    ], 
    "substrates": [
      "C16596", 
      "C00001"
    ]
  }
]