[
  {
    "comment": "unclear reaction incomplete reaction", 
    "definition": "Secologanin <=> Gentiopicrin", 
    "orthologs": {}, 
    "name": "", 
    "product_stoichiometries": [
      "1"
    ], 
    "enzymes": [], 
    "equation": "C01852 <=> C09782", 
    "glycans": false, 
    "substrate_stoichiometries": [
      "1"
    ], 
    "rpairs": {}, 
    "entry_id": "R08500", 
    "pathways": {
      "rn01110": "Biosynthesis of secondary metabolites"
    }, 
    "products": [
      "C09782"
    ], 
    "substrates": [
      "C01852"
    ]
  }
]