[
  {
    "comment": "a part of multi-step reaction (R01001, R08632+R08637) subsequently R08637", 
    "definition": "L-Cystathionine <=> L-Cysteine + 2-Aminobut-2-enoate", 
    "orthologs": {}, 
    "name": "L-cystathionine cysteine-lyase", 
    "product_stoichiometries": [
      "1", 
      "1"
    ], 
    "enzymes": [
      "4.4.1.1"
    ], 
    "equation": "C02291 <=> C00097 + C17234", 
    "glycans": false, 
    "substrate_stoichiometries": [
      "1"
    ], 
    "rpairs": {}, 
    "entry_id": "R08632", 
    "pathways": {}, 
    "products": [
      "C00097", 
      "C17234"
    ], 
    "substrates": [
      "C02291"
    ]
  }
]