[
  {
    "comment": "multi-step reaction (similar to TCA cycle, R01325+R01900+R00709 or R01325+R01900+R01899+R00268)", 
    "definition": "(R)-2-(Phosphonomethyl)malate <=> 2-Oxo-4-phosphonobutanoate", 
    "orthologs": {}, 
    "name": "", 
    "product_stoichiometries": [
      "1"
    ], 
    "enzymes": [], 
    "equation": "C21613 <=> C17941", 
    "glycans": false, 
    "substrate_stoichiometries": [
      "1"
    ], 
    "rpairs": {}, 
    "entry_id": "R08881", 
    "pathways": {
      "rn00440": "Phosphonate and phosphinate metabolism"
    }, 
    "products": [
      "C17941"
    ], 
    "substrates": [
      "C21613"
    ]
  }
]