[
  {
    "comment": "", 
    "definition": "5alpha-Dihydrodeoxycorticosterone + NADPH + H+ <=> Allotetrahydrodeoxycorticosterone + NADP+", 
    "orthologs": {
      "K04119": "aldo-keto reductase family 1 member C3 [EC:1.1.1.51 1.1.1.188 1.1.1.213 1.1.1.357]", 
      "K00089": "3alpha-hydroxysteroid 3-dehydrogenase [EC:1.1.1.213 1.1.1.357]"
    }, 
    "name": "3alpha,21-dihydroxy-5alpha-pregnan-20-one:NADP+ 3-oxidoreductase (A-specific)", 
    "product_stoichiometries": [
      "1", 
      "1"
    ], 
    "enzymes": [
      "1.1.1.213"
    ], 
    "equation": "C18040 + C00005 + C00080 <=> C13713 + C00006", 
    "glycans": false, 
    "substrate_stoichiometries": [
      "1", 
      "1", 
      "1"
    ], 
    "rpairs": {}, 
    "entry_id": "R08955", 
    "pathways": {
      "rn00140": "Steroid hormone biosynthesis"
    }, 
    "products": [
      "C13713", 
      "C00006"
    ], 
    "substrates": [
      "C18040", 
      "C00005", 
      "C00080"
    ]
  }
]