[
  {
    "comment": "", 
    "definition": "Feruloyl-CoA + Putrescine <=> CoA + Feruloylputrescine", 
    "orthologs": {
      "K14329": "agmatine coumaroyltransferase [EC:2.3.1.64 2.3.1.-]"
    }, 
    "name": "feruloyl-CoA:putrescine feruloyltransferase", 
    "product_stoichiometries": [
      "1", 
      "1"
    ], 
    "enzymes": [
      "2.3.1.-"
    ], 
    "equation": "C00406 + C00134 <=> C00010 + C10497", 
    "glycans": false, 
    "substrate_stoichiometries": [
      "1", 
      "1"
    ], 
    "rpairs": {}, 
    "entry_id": "R09257", 
    "pathways": {
      "rn00330": "Arginine and proline metabolism"
    }, 
    "products": [
      "C00010", 
      "C10497"
    ], 
    "substrates": [
      "C00406", 
      "C00134"
    ]
  }
]