[
  {
    "comment": "C7-ketoreductase, snoaF", 
    "definition": "Nogalaviketone + NADPH + H+ <=> Nogalavinone + NADP+", 
    "orthologs": {
      "K15944": "nogalaviketone/aklaviketone reductase [EC:1.1.1.- 1.1.1.362]"
    }, 
    "name": "nogalavinone:NADP+ 7-oxidoreductase", 
    "product_stoichiometries": [
      "1", 
      "1"
    ], 
    "enzymes": [
      "1.1.1.-"
    ], 
    "equation": "C18630 + C00005 + C00080 <=> C18631 + C00006", 
    "glycans": false, 
    "substrate_stoichiometries": [
      "1", 
      "1", 
      "1"
    ], 
    "rpairs": {}, 
    "entry_id": "R09329", 
    "pathways": {
      "rn01130": "Biosynthesis of antibiotics", 
      "rn01057": "Biosynthesis of type II polyketide products"
    }, 
    "products": [
      "C18631", 
      "C00006"
    ], 
    "substrates": [
      "C18630", 
      "C00005", 
      "C00080"
    ]
  }
]