[
  {
    "comment": "", 
    "definition": "Urate + NADH + H+ + Oxygen <=> 5-Hydroxyisourate + NAD+ + H2O", 
    "orthologs": {
      "K16839": "FAD-dependent urate hydroxylase [EC:1.14.13.113]"
    }, 
    "name": "urate,NADH:oxygen oxidoreductase (5-hydroxyisourate forming)", 
    "product_stoichiometries": [
      "1", 
      "1", 
      "1"
    ], 
    "enzymes": [
      "1.14.13.113"
    ], 
    "equation": "C00366 + C00004 + C00080 + C00007 <=> C11821 + C00003 + C00001", 
    "glycans": false, 
    "substrate_stoichiometries": [
      "1", 
      "1", 
      "1", 
      "1"
    ], 
    "rpairs": {}, 
    "entry_id": "R09514", 
    "pathways": {
      "rn00230": "Purine metabolism", 
      "rn01120": "Microbial metabolism in diverse environments", 
      "rn01100": "Metabolic pathways"
    }, 
    "products": [
      "C11821", 
      "C00003", 
      "C00001"
    ], 
    "substrates": [
      "C00366", 
      "C00004", 
      "C00080", 
      "C00007"
    ]
  }
]