[
  {
    "comment": "", 
    "definition": "ATP + 1,6-Anhydro-N-acetyl-beta-muramate + H2O <=> ADP + N-Acetyl-beta-muramate 6-phosphate", 
    "orthologs": {}, 
    "name": "ATP:1,6-anhydro-N-acetylmuramate 6-phosphotransferase", 
    "product_stoichiometries": [
      "1", 
      "1"
    ], 
    "enzymes": [
      "2.7.1.170"
    ], 
    "equation": "C00002 + C19769 + C00001 <=> C00008 + C19770", 
    "glycans": false, 
    "substrate_stoichiometries": [
      "1", 
      "1", 
      "1"
    ], 
    "rpairs": {}, 
    "entry_id": "R09640", 
    "pathways": {}, 
    "products": [
      "C00008", 
      "C19770"
    ], 
    "substrates": [
      "C00002", 
      "C19769", 
      "C00001"
    ]
  }
]