[
  {
    "comment": "", 
    "definition": "Proansamitocin <=> 19-Chloroproansamitocin", 
    "orthologs": {
      "K16033": "FADH2-dependent halogenase"
    }, 
    "name": "", 
    "product_stoichiometries": [
      "1"
    ], 
    "enzymes": [], 
    "equation": "C12177 <=> C20134", 
    "glycans": false, 
    "substrate_stoichiometries": [
      "1"
    ], 
    "rpairs": {}, 
    "entry_id": "R09851", 
    "pathways": {
      "rn01130": "Biosynthesis of antibiotics", 
      "rn01051": "Biosynthesis of ansamycins"
    }, 
    "products": [
      "C20134"
    ], 
    "substrates": [
      "C12177"
    ]
  }
]