[
  {
    "comment": "multi-step reaction intermediate (quinone methide [CPD:C20269])", 
    "definition": "Eugenol + Carboxylate + NADP+ <=> Coniferyl ester + NADPH + H+", 
    "orthologs": {}, 
    "name": "eugenol:NADP+ oxidoreductase (coniferyl ester reducing)", 
    "product_stoichiometries": [
      "1", 
      "1", 
      "1"
    ], 
    "enzymes": [
      "1.1.1.318"
    ], 
    "equation": "C10453 + C00060 + C00006 <=> C20224 + C00005 + C00080", 
    "glycans": false, 
    "substrate_stoichiometries": [
      "1", 
      "1", 
      "1"
    ], 
    "rpairs": {}, 
    "entry_id": "R09930", 
    "pathways": {}, 
    "products": [
      "C20224", 
      "C00005", 
      "C00080"
    ], 
    "substrates": [
      "C10453", 
      "C00060", 
      "C00006"
    ]
  }
]