[
  {
    "comment": "", 
    "definition": "Mycinamicin VIII + NADPH + Oxygen + H+ <=> Mycinamicin VII + NADP+ + H2O", 
    "orthologs": {}, 
    "name": "mycinamicin-VIII,NADPH:oxygen oxidoreductase (21-hydroxylating)", 
    "product_stoichiometries": [
      "1", 
      "1", 
      "1"
    ], 
    "enzymes": [
      "1.14.13.-"
    ], 
    "equation": "C15684 + C00005 + C00007 + C00080 <=> C15683 + C00006 + C00001", 
    "glycans": false, 
    "substrate_stoichiometries": [
      "1", 
      "1", 
      "1", 
      "1"
    ], 
    "rpairs": {}, 
    "entry_id": "R10875", 
    "pathways": {
      "rn01130": "Biosynthesis of antibiotics"
    }, 
    "products": [
      "C15683", 
      "C00006", 
      "C00001"
    ], 
    "substrates": [
      "C15684", 
      "C00005", 
      "C00007", 
      "C00080"
    ]
  }
]