[
  {
    "comment": "", 
    "definition": "ATP + 3-{[(2E)-4-Amino-4-oxobut-2-enoyl]amino}-L-alanine + L-Leucine <=> ADP + Orthophosphate + Dapdiamide C", 
    "orthologs": {}, 
    "name": "3-{[(2E)-4-amino-4-oxobut-2-enoyl]amino}-L-alanine:L-leucine ligase (ADP-forming)", 
    "product_stoichiometries": [
      "1", 
      "1", 
      "1"
    ], 
    "enzymes": [
      "6.3.2.47"
    ], 
    "equation": "C00002 + C20966 + C00123 <=> C00008 + C00009 + C20964", 
    "glycans": false, 
    "substrate_stoichiometries": [
      "1", 
      "1", 
      "1"
    ], 
    "rpairs": {}, 
    "entry_id": "R10944", 
    "pathways": {}, 
    "products": [
      "C00008", 
      "C00009", 
      "C20964"
    ], 
    "substrates": [
      "C00002", 
      "C20966", 
      "C00123"
    ]
  }
]