[
  {
    "comment": "first step of three-step reaction (see R05728, R11442+R04306+R02708)", 
    "definition": "(E)-4-Hydroxyphenylacetaldehyde oxime <=> (Z)-4-Hydroxyphenylacetaldehyde oxime", 
    "orthologs": {
      "K13029": "4-hydroxyphenylacetaldehyde oxime monooxygenase [EC:1.14.14.37]"
    }, 
    "name": "", 
    "product_stoichiometries": [
      "1"
    ], 
    "enzymes": [
      "1.14.14.37"
    ], 
    "equation": "C04350 <=> C04353", 
    "glycans": false, 
    "substrate_stoichiometries": [
      "1"
    ], 
    "rpairs": {}, 
    "entry_id": "R11442", 
    "pathways": {}, 
    "products": [
      "C04353"
    ], 
    "substrates": [
      "C04350"
    ]
  }
]