[
  {
    "comment": "", 
    "definition": "S-[(Z)-N-Hydroxy(phenyl)acetimidoyl]-L-glutathione + H2O <=> (Z)-1-(L-Cysteinylglycine-S-yl)-N-hydroxy-2-phenylethane-1-imine + L-Glutamate", 
    "orthologs": {}, 
    "name": "(Z)-1-(glutathione-S-yl)-N-hydroxy-2-phenylethane-1-imine gamma-glutamyl hydrolase", 
    "product_stoichiometries": [
      "1", 
      "1"
    ], 
    "enzymes": [
      "3.4.19.16"
    ], 
    "equation": "C21622 + C00001 <=> C21667 + C00025", 
    "glycans": false, 
    "substrate_stoichiometries": [
      "1", 
      "1"
    ], 
    "rpairs": {}, 
    "entry_id": "R11795", 
    "pathways": {}, 
    "products": [
      "C21667", 
      "C00025"
    ], 
    "substrates": [
      "C21622", 
      "C00001"
    ]
  }
]