[
  {
    "comment": "", 
    "definition": "ATP + L-Isoleucine + Acetoacetyl-CoA <=> AMP + Diphosphate + Tenuazonic acid + CoA", 
    "orthologs": {}, 
    "name": "L-isoleucine:acetoacetyl-CoA ligase (tenuazonic acid-forming)", 
    "product_stoichiometries": [
      "1", 
      "1", 
      "1", 
      "1"
    ], 
    "enzymes": [
      "6.3.2.50"
    ], 
    "equation": "C00002 + C00407 + C00332 <=> C00020 + C00013 + C08511 + C00010", 
    "glycans": false, 
    "substrate_stoichiometries": [
      "1", 
      "1", 
      "1"
    ], 
    "rpairs": {}, 
    "entry_id": "R11723", 
    "pathways": {}, 
    "products": [
      "C00020", 
      "C00013", 
      "C08511", 
      "C00010"
    ], 
    "substrates": [
      "C00002", 
      "C00407", 
      "C00332"
    ]
  }
]