[
  {
    "comment": "", 
    "definition": "2,3-Diaminopropanoate + H2O <=> Pyruvate + 2 Ammonia", 
    "orthologs": {}, 
    "name": "2,3-diaminopropanoate ammonia-lyase (adding water; pyruvate-forming)", 
    "product_stoichiometries": [
      "2", 
      "1"
    ], 
    "enzymes": [
      "4.3.1.15"
    ], 
    "equation": "C06393 + C00001 <=> C00022 + 2 C00014", 
    "glycans": false, 
    "substrate_stoichiometries": [
      "1", 
      "1"
    ], 
    "rpairs": {}, 
    "entry_id": "R00195", 
    "pathways": {}, 
    "products": [
      "C00014", 
      "C00022"
    ], 
    "substrates": [
      "C06393", 
      "C00001"
    ]
  }
]