[
  {
    "comment": "", 
    "definition": "4-Hydroxybutanoic acid + NAD+ <=> Succinate semialdehyde + NADH + H+", 
    "orthologs": {
      "K00043": "4-hydroxybutyrate dehydrogenase [EC:1.1.1.61]", 
      "K08318": "4-hydroxybutyrate dehydrogenase / sulfolactaldehyde 3-reductase [EC:1.1.1.61 1.1.1.373]", 
      "K18120": "4-hydroxybutyrate dehydrogenase [EC:1.1.1.61]"
    }, 
    "name": "4-hydroxybutanoate:NAD+ oxidoreductase", 
    "product_stoichiometries": [
      "1", 
      "1", 
      "1"
    ], 
    "enzymes": [
      "1.1.1.61"
    ], 
    "equation": "C00989 + C00003 <=> C00232 + C00004 + C00080", 
    "glycans": false, 
    "substrate_stoichiometries": [
      "1", 
      "1"
    ], 
    "rpairs": {}, 
    "entry_id": "R01644", 
    "pathways": {
      "rn00650": "Butanoate metabolism", 
      "rn01100": "Metabolic pathways", 
      "rn01200": "Carbon metabolism"
    }, 
    "products": [
      "C00232", 
      "C00004", 
      "C00080"
    ], 
    "substrates": [
      "C00989", 
      "C00003"
    ]
  }
]