[
  {
    "comment": "", 
    "definition": "CTP + Phosphatidate <=> Diphosphate + CDP-diacylglycerol", 
    "orthologs": {
      "K00981": "phosphatidate cytidylyltransferase [EC:2.7.7.41]"
    }, 
    "name": "CTP:phosphatidate cytidyltransferase", 
    "product_stoichiometries": [
      "1", 
      "1"
    ], 
    "enzymes": [
      "2.7.7.41"
    ], 
    "equation": "C00063 + C00416 <=> C00013 + C00269", 
    "glycans": false, 
    "substrate_stoichiometries": [
      "1", 
      "1"
    ], 
    "rpairs": {}, 
    "entry_id": "R01799", 
    "pathways": {
      "rn00564": "Glycerophospholipid metabolism", 
      "rn01110": "Biosynthesis of secondary metabolites", 
      "rn01100": "Metabolic pathways"
    }, 
    "products": [
      "C00013", 
      "C00269"
    ], 
    "substrates": [
      "C00063", 
      "C00416"
    ]
  }
]