[
  {
    "comment": "a part of multi-step reaction (see R07916, R02065+R07270) subsequently R07270 a part of multi-step reaction (see R10177, R02065+R04218)", 
    "definition": "2 Geranylgeranyl diphosphate <=> Diphosphate + Prephytoene diphosphate", 
    "orthologs": {
      "K02291": "15-cis-phytoene/all-trans-phytoene synthase [EC:2.5.1.32 2.5.1.99]", 
      "K17841": "15-cis-phytoene synthase / lycopene beta-cyclase [EC:2.5.1.32 5.5.1.19]"
    }, 
    "name": "geranylgeranyl-diphosphate:geranylgeranyl-diphosphate geranylgeranyltransferase", 
    "product_stoichiometries": [
      "1", 
      "1"
    ], 
    "enzymes": [
      "2.5.1.32", 
      "2.5.1.99"
    ], 
    "equation": "2 C00353 <=> C00013 + C03427", 
    "glycans": false, 
    "substrate_stoichiometries": [
      "2"
    ], 
    "rpairs": {}, 
    "entry_id": "R02065", 
    "pathways": {
      "rn00906": "Carotenoid biosynthesis", 
      "rn01110": "Biosynthesis of secondary metabolites", 
      "rn01100": "Metabolic pathways"
    }, 
    "products": [
      "C00013", 
      "C03427"
    ], 
    "substrates": [
      "C00353"
    ]
  }
]