[
  {
    "comment": "subsequently R05098", 
    "definition": "2-Hydroxycyclohexan-1-one + Oxygen + NADPH + H+ <=> 6-Hydroxyhexan-6-olide + NADP+ + H2O", 
    "orthologs": {}, 
    "name": "2-hydroxycyclohexan-1-one,NADPH:oxygen 2-oxidoreductase (1,2-lactonizing)", 
    "product_stoichiometries": [
      "1", 
      "1", 
      "1"
    ], 
    "enzymes": [
      "1.14.13.66"
    ], 
    "equation": "C01147 + C00007 + C00005 + C00080 <=> C03241 + C00006 + C00001", 
    "glycans": false, 
    "substrate_stoichiometries": [
      "1", 
      "1", 
      "1", 
      "1"
    ], 
    "rpairs": {}, 
    "entry_id": "R03281", 
    "pathways": {
      "rn00930": "Caprolactam degradation"
    }, 
    "products": [
      "C03241", 
      "C00006", 
      "C00001"
    ], 
    "substrates": [
      "C01147", 
      "C00007", 
      "C00005", 
      "C00080"
    ]
  }
]