[
  {
    "comment": "", 
    "definition": "Pyrimidodiazepine + Glutathione disulfide + H2O <=> 6-Pyruvoyltetrahydropterin + 2 Glutathione", 
    "orthologs": {
      "K00310": "pyrimidodiazepine synthase [EC:1.5.4.1]"
    }, 
    "name": "pyrimidodiazepine:glutathione-disulfide oxidoreductase (ring-opening, cyclizing)", 
    "product_stoichiometries": [
      "2", 
      "1"
    ], 
    "enzymes": [
      "1.5.4.1"
    ], 
    "equation": "C02587 + C00127 + C00001 <=> C03684 + 2 C00051", 
    "glycans": false, 
    "substrate_stoichiometries": [
      "1", 
      "1", 
      "1"
    ], 
    "rpairs": {}, 
    "entry_id": "R03984", 
    "pathways": {
      "rn00480": "Glutathione metabolism", 
      "rn00790": "Folate biosynthesis"
    }, 
    "products": [
      "C00051", 
      "C03684"
    ], 
    "substrates": [
      "C02587", 
      "C00127", 
      "C00001"
    ]
  }
]