[
  {
    "comment": "chlorophenol 4-monooxygenase", 
    "definition": "2,5-Dichlorohydroquinone + FADH2 + Oxygen <=> 5-Chloro-2-hydroxy-p-benzoquinone + FAD + H2O + Cl-", 
    "orthologs": {
      "K15246": "chlorophenol-4-monooxygenase component 2 [EC:1.14.14.-]", 
      "K15245": "chlorophenol-4-monooxygenase component 1 [EC:1.5.1.37]"
    }, 
    "name": "", 
    "product_stoichiometries": [
      "1", 
      "1", 
      "1", 
      "1"
    ], 
    "enzymes": [
      "1.14.14.-"
    ], 
    "equation": "C06600 + C01352 + C00007 <=> C21105 + C00016 + C00001 + C00698", 
    "glycans": false, 
    "substrate_stoichiometries": [
      "1", 
      "1", 
      "1"
    ], 
    "rpairs": {}, 
    "entry_id": "R05446", 
    "pathways": {
      "rn01120": "Microbial metabolism in diverse environments", 
      "rn00361": "Chlorocyclohexane and chlorobenzene degradation", 
      "rn01100": "Metabolic pathways"
    }, 
    "products": [
      "C21105", 
      "C00016", 
      "C00001", 
      "C00698"
    ], 
    "substrates": [
      "C06600", 
      "C01352", 
      "C00007"
    ]
  }
]