[
  {
    "comment": "", 
    "definition": "Protoanemonin + H2O <=> cis-Acetylacrylate", 
    "orthologs": {
      "K01061": "carboxymethylenebutenolidase [EC:3.1.1.45]"
    }, 
    "name": "Protoanemonin lactonohydrolase", 
    "product_stoichiometries": [
      "1"
    ], 
    "enzymes": [
      "3.1.1.45"
    ], 
    "equation": "C07090 + C00001 <=> C07091", 
    "glycans": false, 
    "substrate_stoichiometries": [
      "1", 
      "1"
    ], 
    "rpairs": {}, 
    "entry_id": "R05510", 
    "pathways": {
      "rn01120": "Microbial metabolism in diverse environments", 
      "rn00361": "Chlorocyclohexane and chlorobenzene degradation"
    }, 
    "products": [
      "C07091"
    ], 
    "substrates": [
      "C07090", 
      "C00001"
    ]
  }
]