[
  {
    "comment": "", 
    "definition": "Methyl aklanonate <=> Aklaviketone", 
    "orthologs": {
      "K15943": "nogalonic acid methyl ester cyclase / aklanonic acid methyl ester cyclase [EC:5.5.1.26 5.5.1.23]"
    }, 
    "name": "aklaviketone lyase (ring-opening); methyl aklanonate cyclase", 
    "product_stoichiometries": [
      "1"
    ], 
    "enzymes": [
      "5.5.1.23"
    ], 
    "equation": "C12422 <=> C12423", 
    "glycans": false, 
    "substrate_stoichiometries": [
      "1"
    ], 
    "rpairs": {}, 
    "entry_id": "R06681", 
    "pathways": {
      "rn01130": "Biosynthesis of antibiotics", 
      "rn01057": "Biosynthesis of type II polyketide products"
    }, 
    "products": [
      "C12423"
    ], 
    "substrates": [
      "C12422"
    ]
  }
]