[
  {
    "comment": "", 
    "definition": "Xylitol + Oxygen <=> D-Xylose + Hydrogen peroxide", 
    "orthologs": {
      "K00594": "alditol oxidase [EC:1.1.3.41]"
    }, 
    "name": "xylitol:oxygen oxidoreductase", 
    "product_stoichiometries": [
      "1", 
      "1"
    ], 
    "enzymes": [
      "1.1.3.41"
    ], 
    "equation": "C00379 + C00007 <=> C00181 + C00027", 
    "glycans": false, 
    "substrate_stoichiometries": [
      "1", 
      "1"
    ], 
    "rpairs": {}, 
    "entry_id": "R07152", 
    "pathways": {
      "rn00040": "Pentose and glucuronate interconversions", 
      "rn01100": "Metabolic pathways"
    }, 
    "products": [
      "C00181", 
      "C00027"
    ], 
    "substrates": [
      "C00379", 
      "C00007"
    ]
  }
]