[
  {
    "comment": "", 
    "definition": "L-Galactono-1,4-lactone + H2O <=> L-Galactonate", 
    "orthologs": {}, 
    "name": "", 
    "product_stoichiometries": [
      "1"
    ], 
    "enzymes": [
      "3.1.1.-"
    ], 
    "equation": "C01115 + C00001 <=> C15930", 
    "glycans": false, 
    "substrate_stoichiometries": [
      "1", 
      "1"
    ], 
    "rpairs": {}, 
    "entry_id": "R07680", 
    "pathways": {
      "rn00053": "Ascorbate and aldarate metabolism"
    }, 
    "products": [
      "C15930"
    ], 
    "substrates": [
      "C01115", 
      "C00001"
    ]
  }
]