[
  {
    "comment": "", 
    "definition": "5,10-Methylenetetrahydromethanopterin + NADP+ <=> 5,10-Methenyltetrahydromethanopterin + NADPH", 
    "orthologs": {
      "K10714": "methylene-tetrahydromethanopterin dehydrogenase [EC:1.5.1.-]"
    }, 
    "name": "", 
    "product_stoichiometries": [
      "1", 
      "1"
    ], 
    "enzymes": [
      "1.5.1.-"
    ], 
    "equation": "C04377 + C00006 <=> C04330 + C00005", 
    "glycans": false, 
    "substrate_stoichiometries": [
      "1", 
      "1"
    ], 
    "rpairs": {}, 
    "entry_id": "R08059", 
    "pathways": {
      "rn00680": "Methane metabolism", 
      "rn01120": "Microbial metabolism in diverse environments", 
      "rn01100": "Metabolic pathways", 
      "rn01200": "Carbon metabolism"
    }, 
    "products": [
      "C04330", 
      "C00005"
    ], 
    "substrates": [
      "C04377", 
      "C00006"
    ]
  }
]