[
  {
    "comment": "a part of multi-step reaction (R00781, R08677+R08678) following after R08677", 
    "definition": "S-Sulfanylglutathione + Oxygen + H2O <=> Glutathione + Sulfite", 
    "orthologs": {}, 
    "name": "S-sulfanylglutathione:oxygen oxidoreductase", 
    "product_stoichiometries": [
      "1", 
      "1"
    ], 
    "enzymes": [
      "1.13.11.18"
    ], 
    "equation": "C17267 + C00007 + C00001 <=> C00051 + C00094", 
    "glycans": false, 
    "substrate_stoichiometries": [
      "1", 
      "1", 
      "1"
    ], 
    "rpairs": {}, 
    "entry_id": "R08678", 
    "pathways": {}, 
    "products": [
      "C00051", 
      "C00094"
    ], 
    "substrates": [
      "C17267", 
      "C00007", 
      "C00001"
    ]
  }
]