[
  {
    "comment": "two-step reaction (see R09576+R09577)", 
    "definition": "Vetispiradiene + 2 NADPH + 2 H+ + 2 Oxygen <=> Solavetivone + 2 NADP+ + 3 H2O", 
    "orthologs": {
      "K15472": "premnaspirodiene oxygenase [EC:1.14.13.121]"
    }, 
    "name": "(-)-vetispiradiene,NADPH:oxygen 2alpha-oxidoreductase", 
    "product_stoichiometries": [
      "2", 
      "3", 
      "1"
    ], 
    "enzymes": [
      "1.14.13.121"
    ], 
    "equation": "C12142 + 2 C00005 + 2 C00080 + 2 C00007 <=> C09737 + 2 C00006 + 3 C00001", 
    "glycans": false, 
    "substrate_stoichiometries": [
      "2", 
      "2", 
      "2", 
      "1"
    ], 
    "rpairs": {}, 
    "entry_id": "R10073", 
    "pathways": {}, 
    "products": [
      "C00006", 
      "C00001", 
      "C09737"
    ], 
    "substrates": [
      "C00005", 
      "C00080", 
      "C00007", 
      "C12142"
    ]
  }
]