[
  {
    "comment": "", 
    "definition": "[(1R)-2,2,3-Trimethyl-5-oxocyclopent-3-enyl]acetyl-CoA + Oxygen + NADPH + H+ <=> [(2R)-3,3,4-Trimethyl-6-oxo-3,6-dihydro-1H-pyran-2-yl]acetyl-CoA + NADP+ + H2O", 
    "orthologs": {}, 
    "name": "[(1R)-2,2,3-trimethyl-5-oxocyclopent-3-enyl]acetyl-CoA,NADPH:oxygen oxidoreductase (1,5-lactonizing)", 
    "product_stoichiometries": [
      "1", 
      "1", 
      "1"
    ], 
    "enzymes": [
      "1.14.13.160"
    ], 
    "equation": "C07160 + C00007 + C00005 + C00080 <=> C20321 + C00006 + C00001", 
    "glycans": false, 
    "substrate_stoichiometries": [
      "1", 
      "1", 
      "1", 
      "1"
    ], 
    "rpairs": {}, 
    "entry_id": "R10044", 
    "pathways": {}, 
    "products": [
      "C20321", 
      "C00006", 
      "C00001"
    ], 
    "substrates": [
      "C07160", 
      "C00007", 
      "C00005", 
      "C00080"
    ]
  }
]