[
  {
    "comment": "", 
    "definition": "Hydroxylamine + 3 Ferricytochrome c <=> Nitric oxide + 3 Ferrocytochrome c + 3 H+", 
    "orthologs": {}, 
    "name": "hydroxylamine:ferricytochrome-c oxidoreductase", 
    "product_stoichiometries": [
      "3", 
      "3", 
      "1"
    ], 
    "enzymes": [
      "1.7.2.6"
    ], 
    "equation": "C00192 + 3 C00125 <=> C00533 + 3 C00126 + 3 C00080", 
    "glycans": false, 
    "substrate_stoichiometries": [
      "3", 
      "1"
    ], 
    "rpairs": {}, 
    "entry_id": "R10165", 
    "pathways": {}, 
    "products": [
      "C00126", 
      "C00080", 
      "C00533"
    ], 
    "substrates": [
      "C00125", 
      "C00192"
    ]
  }
]