[
  {
    "comment": "first step of two-step reaction (see R09603, R10843+R10844)", 
    "definition": "Zeaxanthin + Oxygen <=> beta-Citraurin + (3S)-3-Hydroxycyclocitral", 
    "orthologs": {}, 
    "name": "zeaxanthin:oxygen oxidoreductase (7,8-cleaving)", 
    "product_stoichiometries": [
      "1", 
      "1"
    ], 
    "enzymes": [
      "1.14.99.42"
    ], 
    "equation": "C06098 + C00007 <=> C20894 + C19731", 
    "glycans": false, 
    "substrate_stoichiometries": [
      "1", 
      "1"
    ], 
    "rpairs": {}, 
    "entry_id": "R10843", 
    "pathways": {}, 
    "products": [
      "C20894", 
      "C19731"
    ], 
    "substrates": [
      "C06098", 
      "C00007"
    ]
  }
]