[
  {
    "comment": "", 
    "definition": "S-Adenosyl-L-methionine + 4-Amino-anhydrotetracycline <=> S-Adenosyl-L-homocysteine + 4-Methylamino-4-de(dimethylamino)anhydrotetracycline", 
    "orthologs": {
      "K14255": "4-amino-anhydrotetracycline N4-methyltransferase [EC:2.1.1.335]"
    }, 
    "name": "S-adenosyl-L-methionine:4-amino-anhydrotetracycline N-methyltransferase", 
    "product_stoichiometries": [
      "1", 
      "1"
    ], 
    "enzymes": [
      "2.1.1.335"
    ], 
    "equation": "C00019 + C06654 <=> C00021 + C21436", 
    "glycans": false, 
    "substrate_stoichiometries": [
      "1", 
      "1"
    ], 
    "rpairs": {}, 
    "entry_id": "R11520", 
    "pathways": {}, 
    "products": [
      "C00021", 
      "C21436"
    ], 
    "substrates": [
      "C00019", 
      "C06654"
    ]
  }
]