[
  {
    "comment": "radical SAM", 
    "definition": "12-Ethyl-8-propyl-3-vinylbacteriochlorophyllide d + S-Adenosyl-L-methionine <=> 12-Ethyl-8-isobutyl-3-vinylbacteriochlorophyllide d + S-Adenosyl-L-homocysteine", 
    "orthologs": {
      "K13601": "bacteriochlorophyllide d C-8(2)-methyltransferase [EC:2.1.1.332]"
    }, 
    "name": "S-adenosyl-L-methionine:12-ethyl-8-propyl-3-vinylbacteriochlorophyllide d C-8(2)-methyltransferase", 
    "product_stoichiometries": [
      "1", 
      "1"
    ], 
    "enzymes": [
      "2.1.1.332"
    ], 
    "equation": "C21428 + C00019 <=> C21429 + C00021", 
    "glycans": false, 
    "substrate_stoichiometries": [
      "1", 
      "1"
    ], 
    "rpairs": {}, 
    "entry_id": "R11509", 
    "pathways": {
      "rn01110": "Biosynthesis of secondary metabolites", 
      "rn00860": "Porphyrin and chlorophyll metabolism"
    }, 
    "products": [
      "C21429", 
      "C00021"
    ], 
    "substrates": [
      "C21428", 
      "C00019"
    ]
  }
]