[
  {
    "comment": "", 
    "definition": "Cephaeline + S-Adenosyl-L-methionine <=> Emetine + S-Adenosyl-L-homocysteine", 
    "orthologs": {
      "K22091": "O-methyltransferase [EC:2.1.1.-]"
    }, 
    "name": "S-adenosyl-L-methionine:cephaeline O-methyltransferase", 
    "product_stoichiometries": [
      "1", 
      "1"
    ], 
    "enzymes": [
      "2.1.1.-"
    ], 
    "equation": "C09390 + C00019 <=> C09421 + C00021", 
    "glycans": false, 
    "substrate_stoichiometries": [
      "1", 
      "1"
    ], 
    "rpairs": {}, 
    "entry_id": "R11686", 
    "pathways": {
      "rn01110": "Biosynthesis of secondary metabolites", 
      "rn00950": "Isoquinoline alkaloid biosynthesis"
    }, 
    "products": [
      "C09421", 
      "C00021"
    ], 
    "substrates": [
      "C09390", 
      "C00019"
    ]
  }
]