[
  {
    "comment": "", 
    "definition": "UDP-alpha-D-galactose + N-Acetyl-beta-D-glucosaminide <=> UDP + 1,3-beta-D-Galactosyl-N-acetyl-D-glucosaminyl-R", 
    "orthologs": {}, 
    "name": "UDP-alpha-D-galactose:N-acetyl-beta-D-glucosaminyl-R 3-beta-D-galactosyltransferase", 
    "product_stoichiometries": [
      "1", 
      "1"
    ], 
    "enzymes": [
      "2.4.1.86"
    ], 
    "equation": "C00052 + C03518 <=> C00015 + C04656", 
    "glycans": false, 
    "substrate_stoichiometries": [
      "1", 
      "1"
    ], 
    "rpairs": {}, 
    "entry_id": "R11714", 
    "pathways": {}, 
    "products": [
      "C00015", 
      "C04656"
    ], 
    "substrates": [
      "C00052", 
      "C03518"
    ]
  }
]